{
  "rooms": {
    "hyp": {
      "users": {},
      "board": [
        "",
        "",
        "",
        "",
        "",
        "",
        "",
        "",
        ""
      ],
      "num": 0,
      "passcode": "",
      "circleTurn": false,
      "roundWon": false
    },
    "hello": {
      "users": {},
      "board": [
        "",
        "",
        "",
        "",
        "",
        "",
        "",
        "",
        ""
      ],
      "num": 0,
      "passcode": "",
      "circleTurn": false,
      "roundWon": false
    }
  }
}